larning/__init__.py
larning/abc.py
larning/abc_i.py
larning/abc_test.py
larning/ci.py
larning/ci_test.py
larning/iter_test.py
larning/logging.py
larning/logging_i.py
larning/logging_test.py
larning/metaclass.py
larning/metaclass_i.py
larning/metaclass_test.py
larning/os.py
larning/os_test.py
larning/other_test.py
larning/property.py
larning/property_test.py
larning/re.py
larning/re_i.py
larning/re_test.py
larning/setup.py
larning/setup_i.py
larning/setup_test.py
larning/strings.py
larning/strings_i.py
larning/strings_test.py
larning/testing.py
larning/testing_i.py
larning/testing_test.py
larning/null/__init__.py
larning/null/_test.py
larning/null/i.py
larning/output/__init__.py
larning/output/i.py
larning-0.0.10.dist-info/LICENSE
larning-0.0.10.dist-info/METADATA
larning-0.0.10.dist-info/WHEEL
larning-0.0.10.dist-info/top_level.txt
larning-0.0.10.dist-info/RECORD
